difft/__init__.py
difft/attachment.py
difft/auth.py
difft/client.py
difft/command.py
difft/constants.py
difft/crypto.py
difft/difft_ws_listener.py
difft/message.py
difft/utils.py
difft-1.4.9.dist-info/METADATA
difft-1.4.9.dist-info/WHEEL
difft-1.4.9.dist-info/entry_points.txt
difft-1.4.9.dist-info/top_level.txt
difft-1.4.9.dist-info/RECORD
