Metadata-Version: 2.4
Name: difft
Version: 1.4.9
Summary: Python Distribution Utilities
Home-page: 
Author: difft.org
Author-email: teams@difft.org
Requires-Python: >=3.6
Requires-Dist: requests
Requires-Dist: pycryptodome
Requires-Dist: websocket-client
Requires-Dist: rel
Dynamic: author
Dynamic: author-email
Dynamic: requires-dist
Dynamic: requires-python
Dynamic: summary
